COPYING.LESSER
LICENSE
MANIFEST.in
README.md
setup.py
django_simple_links.egg-info/PKG-INFO
django_simple_links.egg-info/SOURCES.txt
django_simple_links.egg-info/dependency_links.txt
django_simple_links.egg-info/not-zip-safe
django_simple_links.egg-info/top_level.txt
simple_links/__init__.py
simple_links/admin.py
simple_links/managers.py
simple_links/models.py
simple_links/views.py
simple_links/migrations/0001_initial.py
simple_links/migrations/__init__.py
simple_links/templatetags/__init__.py
simple_links/templatetags/link_list.py